crosswalk/__init__.py
crosswalk/admin.py
crosswalk/apps.py
crosswalk/authentication.py
crosswalk/exceptions.py
crosswalk/serializers.py
crosswalk/signals.py
crosswalk/urls.py
crosswalk/utils.py
crosswalk/validators.py
crosswalk/views.py
crosswalk/viewsets.py
crosswalk/management/__init__.py
crosswalk/management/commands/__init__.py
crosswalk/migrations/0001_initial.py
crosswalk/migrations/0002_auto_20190409_0153.py
crosswalk/migrations/__init__.py
crosswalk/models/__init__.py
crosswalk/models/domain.py
crosswalk/models/entity.py
crosswalk/models/user.py
crosswalk/scorers/__init__.py
crosswalk/scorers/fuzzywuzzy.py
crosswalk/views/__init__.py
crosswalk/views/alias_or_create.py
crosswalk/views/best_match.py
crosswalk/views/best_match_or_create.py
crosswalk/views/bulk_create.py
crosswalk/views/client_check.py
crosswalk/views/delete_match.py
crosswalk/views/match.py
crosswalk/views/match_or_create.py
crosswalk/views/update_match.py
django_crosswalk-0.0.13.dist-info/LICENSE
django_crosswalk-0.0.13.dist-info/METADATA
django_crosswalk-0.0.13.dist-info/WHEEL
django_crosswalk-0.0.13.dist-info/top_level.txt
django_crosswalk-0.0.13.dist-info/RECORD
