Metadata-Version: 2.1
Name: django-crosswalk
Version: 0.0.13
Summary: Build and query databases of arbitrary entities.
Home-page: https://github.com/The-Politico/django-crosswalk
License: MIT
Platform: UNKNOWN
Classifier: Environment :: Web Environment
Classifier: Framework :: Django
Classifier: Intended Audience :: Developers
Classifier: License :: OSI Approved :: MIT License
Classifier: Operating System :: OS Independent
Classifier: Programming Language :: Python
Classifier: Programming Language :: Python :: 3
Classifier: Programming Language :: Python :: 3.5
Classifier: Programming Language :: Python :: 3.6
Classifier: Topic :: Internet :: WWW/HTTP
Classifier: Topic :: Internet :: WWW/HTTP :: Dynamic Content
Requires-Python: >=3.6
Requires-Dist: django (>=2.2)
Requires-Dist: djangorestframework
Requires-Dist: django-filter
Requires-Dist: django-uuslug
Requires-Dist: python-Levenshtein
Requires-Dist: fuzzywuzzy
